dserver_notification_plugin/__init__.py
dserver_notification_plugin/config.py
dserver_notification_plugin/version.py
dserver_notification_plugin-0.4.3.dist-info/LICENSE
dserver_notification_plugin-0.4.3.dist-info/METADATA
dserver_notification_plugin-0.4.3.dist-info/WHEEL
dserver_notification_plugin-0.4.3.dist-info/entry_points.txt
dserver_notification_plugin-0.4.3.dist-info/top_level.txt
dserver_notification_plugin-0.4.3.dist-info/RECORD
