Metadata-Version: 2.1
Name: dserver-notification-plugin
Version: 0.4.3
Summary: dserver plugin for receiving s3 notifications on updated objects.
Author-email: Lars Pastewka <lars.pastewka@imtek.uni-freiburg.de>, "Johannes L. Hörmann" <johannes.laurin@gmail.com>
License: MIT License
Project-URL: Documentation, https://dserver-notification-plugin.readthedocs.io
Project-URL: Repository, https://github.com/livMatS/dserver-notification-plugin
Project-URL: Changelog, https://github.com/livMatS/dserver-notification-plugin/blob/main/CHANGELOG.rst
License-File: LICENSE
Requires-Dist: dtoolcore >=3.18.0
Requires-Dist: dtool-s3
Requires-Dist: dservercore >0.18.0
Provides-Extra: test
Requires-Dist: dservercore ; extra == 'test'
Requires-Dist: dserver-retrieve-plugin-mongo ; extra == 'test'
Requires-Dist: dserver-search-plugin-mongo ; extra == 'test'
Requires-Dist: pytest ; extra == 'test'
Requires-Dist: pytest-cov ; extra == 'test'
